{
	"animations": [
		{
			"loop": false,
			"offsets": [
				-5,
				0
			],
			"anim": "idle",
			"fps": 24,
			"name": "JBbf idle",
			"indices": []
		},
		{
			"loop": false,
			"offsets": [
				5,
				-6
			],
			"anim": "singLEFT",
			"fps": 24,
			"name": "JBbf sing left",
			"indices": []
		},
		{
			"loop": false,
			"offsets": [
				-20,
				-51
			],
			"anim": "singDOWN",
			"fps": 24,
			"name": "JBbf sing down",
			"indices": []
		},
		{
			"loop": false,
			"offsets": [
				-46,
				27
			],
			"anim": "singUP",
			"fps": 24,
			"name": "JBbf sing up",
			"indices": []
		},
		{
			"loop": false,
			"offsets": [
				-48,
				-7
			],
			"anim": "singRIGHT",
			"fps": 24,
			"name": "JBbf sing right",
			"indices": []
		},
		{
			"loop": false,
			"offsets": [
				7,
				19
			],
			"anim": "singLEFTmiss",
			"fps": 24,
			"name": "JBbf left miss",
			"indices": []
		},
		{
			"loop": false,
			"offsets": [
				-15,
				-19
			],
			"anim": "singDOWNmiss",
			"fps": 24,
			"name": "JBbf down miss",
			"indices": []
		},
		{
			"loop": false,
			"offsets": [
				-46,
				27
			],
			"anim": "singUPmiss",
			"fps": 24,
			"name": "JBbf up miss",
			"indices": []
		},
		{
			"loop": false,
			"offsets": [
				-44,
				22
			],
			"anim": "singRIGHTmiss",
			"fps": 24,
			"name": "JBbf right miss",
			"indices": []
		}
	],
	"no_antialiasing": false,
	"gameover_properties": [
		"bf-dead",
		"fnf_loss_sfx",
		"gameOver",
		"gameOverEnd"
	],
	"image": "characters/JBBF",
	"position": [
		0,
		350
	],
	"healthicon": "JBBF",
	"flip_x": true,
	"healthbar_colors": [
		204,
		100,
		0
	],
	"camera_position": [
		0,
		0
	],
	"sing_duration": 4,
	"scale": 1
}